Workbook

Sheet Summary
B1: TOUR BUDGET · SUMMARY
B2: All figures linked directly to individual sheets · Fill each tab → Summary updates automatically
B4: Artist name:
B5: Tour name:
B6: Currency:
B8: OPERATION | C8: PERIOD | D8: TOTAL COST | E8: TOTAL REVENUES | F8: MERCH MARGIN | G8: NET RESULT | H8: CUMULATIVE NET RESULT
B9: Pre-Production | C9: =IFERROR(IF(AND('Pre-Production'!C4<>"", 'Pre-Production'!C5<>""), TEXT('Pre-Production'!C4,"DD/MM/YY")&" → "&TEXT('Pre-Production'!C5,"DD/MM/YY"),""),"") | D9: ='Pre-Production'!E75 -> 0 | E9: ='Pre-Production'!E88 -> 0 | F9: 0 | G9: =-'Pre-Production'!E92 -> 0 | H9: =G9 -> 0
B10: Release Show | C10: =IFERROR(IF('Release Show'!C8<>"",TEXT('Release Show'!C8,"DD/MM/YY"),""),"") | D10: ='Release Show'!E66 -> 0 | E10: ='Release Show'!H28 -> 0 | F10: ='Release Show'!H57 -> 0 | G10: ='Release Show'!H59 -> 0 | H10: =H9+G10 -> 0
B11: Regional Tour | C11: =IFERROR(IF(AND('Regional Tour'!C9<>"",'Regional Tour'!C10<>""),TEXT('Regional Tour'!C9,"DD/MM/YY")&" → "&TEXT('Regional Tour'!C10,"DD/MM/YY"),""),"") | D11: ='Regional Tour'!D85 -> 0 | E11: ='Regional Tour'!E102 -> 0 | F11: ='Regional Tour'!E112 -> 0 | G11: ='Regional Tour'!E116 -> 0 | H11: =H10+G11 -> 0
B12: International Tour | C12: =IFERROR(IF(AND('International Tour'!C9<>"",'International Tour'!C10<>""),TEXT('International Tour'!C9,"DD/MM/YY")&" → "&TEXT('International Tour'!C10,"DD/MM/YY"),""),"") | D12: ='International Tour'!D85 -> 0 | E12: ='International Tour'!E102 -> 0 | F12: ='International Tour'!E112 -> 0 | G12: ='International Tour'!E116 -> 0 | H12: =H11+G12 -> 0
B13: Major Show | C13: =IFERROR(IF('Major Show'!C8<>"",TEXT('Major Show'!C8,"DD/MM/YY"),""),"") | D13: ='Major Show'!E69 -> 0 | E13: ='Major Show'!H28 -> 0 | F13: ='Major Show'!H57 -> 0 | G13: ='Major Show'!H59 -> 0 | H13: =H12+G13 -> 0
B15: TOTAL | D15: =SUM(D9:D13) -> 0 | E15: =SUM(E9:E13) -> 0 | F15: =SUM(F9:F13) -> 0 | G15: =SUM(G9:G13) -> 0 | H15: =H13 -> 0
B19: PROJECT TIMELINE
B21: PHASE | C21: START DATE | D21: END DATE | E21: DURATION (days) | F21: DURATION (months)
B22: Pre-Production | C22: ='Pre-Production'!C4 -> 0 | D22: ='Pre-Production'!C5 -> 0 | E22: ='Pre-Production'!C6 | F22: ='Pre-Production'!D6
B23: Release Show | C23: ='Release Show'!C8 -> 0 | D23: ='Release Show'!C8 -> 0
B24: Regional Tour | C24: ='Regional Tour'!C9 -> 0 | D24: ='Regional Tour'!C10 -> 0 | E24: ='Regional Tour'!C11 | F24: ='Regional Tour'!D11
B25: International Tour | C25: ='International Tour'!C9 -> 0 | D25: ='International Tour'!C10 -> 0 | E25: ='International Tour'!C11 | F25: ='International Tour'!D11
B26: Major Show | C26: ='Major Show'!C8 -> 0 | D26: ='Major Show'!C8 -> 0
B28: TOTAL PROJECT DURATION
B30: ★ Colour code: Blue = input · Black = formula · ★ = key assumption to define with group · All amounts in JOD (changeable)

Sheet Pre-Production
B1: PRE-PRODUCTION · REHEARSALS & CREATIVE RESIDENCY
B2: Artist: | C2: =Summary!C4 -> 0
B3: Tour name:
B4: Start date:
B5: End date:
B6: Duration: | C6: =IF(AND(C4<>"",C5<>""),C5-C4,"") | D6: =IF(AND(C4<>"",C5<>""),ROUND((C5-C4)/30,1),"")
B7: Nb Rehearsal Days:
B8: Nb Residency Days:
B10: ★ EMPLOYER SOCIAL CHARGES RATE (define with group)
B11: ★ FOREIGN ARTIST WITHHOLDING TAX RATE (define with group)
B12: ★ MANAGEMENT COMMISSION RATE (define with group)
B14: POSITION | C14: FEE / DAY | D14: NB DAYS | E14: TOTAL
B15: Artist Bill
B16: Singer | E16: =C16*D16 -> 0
B17: Keys | E17: =C17*D17 -> 0
B18: Drummer | E18: =C18*D18 -> 0
B19: Bass | E19: =C19*D19 -> 0
E20: =C20*D20 -> 0
E21: =C21*D21 -> 0
B22: Musician (foreign artist) | E22: =C22*D22 -> 0
B23: Subtotal gross fees | E23: =SUM(E16:E22) -> 0
B24: Employer social charges (★) — local musicians | E24: =E10*(E16+E17+E18+E19+E20) -> 0
B25: Withholding tax (★) — foreign artists | E25: =E11*(E21+E22) -> 0
B26: TOTAL ARTIST BILL PAYROLL | E26: =E23+E24+E25 -> 0
B28: Technical Crew
B29: General Stage Manager | E29: =C29*D29 -> 0
B30: Sound Engineer (FOH) | E30: =C30*D30 -> 0
B31: Lighting Designer | E31: =C31*D31 -> 0
B32: Backline Tech | E32: =C32*D32 -> 0
B33: Wardrobe / Styling | E33: =C33*D33 -> 0
B34: Roads / Crew | E34: =C34*D34 -> 0
B35: Runner | E35: =C35*D35 -> 0
B36: Subtotal gross fees | E36: =SUM(E29:E35) -> 0
B37: Employer social charges (★) | E37: =E10*E36 -> 0
B38: Withholding tax (★) — foreign tech (if any) | E38: =E11*0 -> 0
B39: TOTAL TECHNICAL CREW PAYROLL | E39: =E36+E37+E38 -> 0
B41: Creative & Technical Costs
B42: Studio / Rehearsal Room Rental | E42: =C42*D42 -> 0
B43: Residency Venue | E43: =C43*D43 -> 0
E44: =C44*D44 -> 0
B45: Sound Equipment Rental | E45: =C45*D45 -> 0
B46: Backline / Flight Cases Purchase | E46: =C46*D46 -> 0
B47: Stage Design / Set | E47: =C47*D47 -> 0
B48: Posters / Artwork / Printing | E48: =C48*D48 -> 0
B49: Costumes & Styling | E49: =C49*D49 -> 0
B50: In-ear Monitors Purchase | E50: =C50*D50 -> 0
B51: Miscellaneous | E51: =C51*D51 -> 0
B52: TOTAL CREATIVE & TECHNICAL COSTS | E52: =SUM(E42:E51) -> 0
B54: Transport
B55: Artists (rehearsals) | E55: =C55*D55 -> 0
B56: Tech Crew (rehearsals) | E56: =C56*D56 -> 0
B57: Artists (residency) | E57: =C57*D57 -> 0
B58: Tech Crew (residency) | E58: =C58*D58 -> 0
B59: Equipment / Gear | E59: =C59*D59 -> 0
B60: Fuel / Tolls | E60: =C60*D60 -> 0
B61: Miscellaneous | E61: =C61*D61 -> 0
B62: TOTAL TRANSPORT | E62: =SUM(E55:E61) -> 0
B64: Accommodation & Meals
B65: Artists – Rehearsal period | E65: =C65*D65 -> 0
B66: Tech – Rehearsal period | E66: =C66*D66 -> 0
B67: Artists – Residency | E67: =C67*D67 -> 0
B68: Tech – Residency | E68: =C68*D68 -> 0
B69: Meals / Catering | C69: =160 -> 160 | E69: =C69*D69 -> 0
B70: Miscellaneous | E70: =C70*D70 -> 0
B71: TOTAL ACCOMMODATION & MEALS | E71: =SUM(E65:E70) -> 0
B75: TOTAL PRE-PRODUCTION COST | E75: =E26+E39+E52+E62+E71 -> 0
B77: Management Com | E77: =E12*E75 -> 0
B81: INCOME & FUNDING — Creation phase
B82: SOURCE | C82: DETAILS / NOTES | E82: AMOUNT
B83: Public grant / subsidy (IFJ, AFAC, Goethe…)
B84: Private sponsorship / mécénat
B85: Artist residency hosting fee
B86: Crowdfunding
B87: Other income
B88: TOTAL FUNDING | E88: =SUM(E83:E87) -> 0
B92: NET COST TO ARTIST = Total Cost + Mgmt Commission – Funding | E92: =E75+E77-E88 -> 0

Sheet Release Show
B1: RELEASE SHOW · SELF-PRODUCED DATE
B2: ★ EMPLOYER SOCIAL CHARGES RATE
B3: ★ FOREIGN ARTIST WITHHOLDING TAX
B4: ★ MANAGEMENT COMMISSION RATE
B5: ★ BOOKING AGENT COMMISSION RATE
B7: Artist: | C7: =Summary!C4 -> 0
B8: Date:
B9: Venue:
B10: City:
B11: Capacity (Jauge):
B13: EXPENSES | C13: UNIT COST | D13: QTY | E13: TOTAL HT | G13: TICKETING STRUCTURE
B14: Venue | G14: Capacity (Jauge)
B15: Venue rental (fixed fee) | E15: =C15*D15 -> 0 | G15: Invitations (comps)
B16: Venue rental (variable %) | E16: =C16*D16 -> 0 | G16: Venue servitudes
B17: Video recording / Broadcast | E17: =C17*D17 -> 0 | G17: Tickets to sell | H17: =H14-H15-H16 -> 0
B18: Overtime hours | E18: =C18*D18 -> 0
B19: Ticketing / box-office fees | E19: =C19*D19 -> 0 | G19: TICKET PRICES
G20: Early Bird price
B21: Security provision | E21: =C20*D20 -> 0 | G21: Presale price
B22: Subtotal Venue | E22: =SUM(E15:E20) -> 0 | G22: Door price — auto: presale × 1.25 | H22: =H21*1.25 -> 0
B24: Artist Bill (incl. payroll charges) | G24: TICKET SALES
G25: Early Bird tickets sold
G26: Early Bird revenue | H26: =H20*H25 -> 0
B27: Singer | E27: =C24*D24 -> 0 | G27: Presale tickets sold
B28: Keys | E28: =C25*D25 -> 0 | G28: Presale revenue | H28: =H21*H27 -> 0
B29: Bass Player | E29: =C26*D26 -> 0 | G29: Door tickets sold
B30: Drums | E30: =C27*D27 -> 0 | G30: Door revenue | H30: =H22*H29 -> 0
B31: Musician (foreign artist) | E31: =C28*D28 -> 0 | G31: GROSS TICKET REVENUE (TTC) | H31: =H26+H28+H30 -> 0
B32: Musician (foreign artist) | E32: =C29*D29 -> 0
B33: Subtotal gross fees (Artist Bill) | E33: =SUM(E24:E29) -> 0 | G33: TAXES & DEDUCTIONS (Jordan)
B34: Employer social charges (★) — local musicians | E34: =E2*(E24+E25+E26+E27) -> 0 | G34: GST / Sales Tax on tickets (~16% Jordan — to confirm) | H34: =0.16*H31 -> 0
B35: Withholding tax (★) — foreign artists | G35: Entertainment / ticketing tax (rate TBC)
B36: TOTAL ARTIST BILL PAYROLL | E36: =E30+E31+E32 -> 0 | G36: Other local levies
G37: TOTAL TAXES & DEDUCTIONS | H37: =SUM(H34:H36) -> 0
B38: Production Tech | G38: NET TICKET REVENUE | H38: =H28-H34 -> 0
B39: Sound system rental | E39: =C36*D36 -> 0
B40: Lighting rig rental | E40: =C37*D37 -> 0 | G40: OTHER REVENUES
B41: Video / LED wall | E41: =C38*D38 -> 0 | G41: Sponsorship / brand partnership
B42: Backline rental | E42: =C39*D39 -> 0
B43: Rigging / Stage | E43: =C40*D40 -> 0 | G43: TOTAL OTHER REVENUES | H43: =H38+H39 -> 0
B44: Special effects | E44: =C41*D41 -> 0
B45: Miscellaneous | G45: COMMISSIONS
B46: Subtotal Production Tech | E46: =SUM(E36:E42) -> 0 | G46: Management commission (★)
G47: Booking agent commission (★) | H47: =E5*H35 -> 0
B48: Marketing & Promotion
B49: Social media ads (Meta / TikTok / YouTube) | E49: =C46*D46 -> 0 | G49: BREAK-EVEN
B50: Radio / TV spots | E50: =C47*D47 -> 0 | G50: Min tickets to sell (total expenses ÷ avg net price)
B51: Print (posters, flyers, banners) | E51: =C48*D48 -> 0 | G51: Break-even as % of capacity | H51: =IFERROR(ROUND(E66/((H35)/(H24+H26+1))/H14,3),"fill data") -> fill data
B52: Press / PR agency fees | E52: =C49*D49 -> 0
B53: Street marketing / crew | G53: MERCHANDISE
B54: Subtotal Marketing & Promotion | E54: =SUM(E46:E50) -> 0 | G54: PRODUCT | H54: UNIT COST | I54: SELLING PRICE | J54: QTY SOLD | K54: NET MARGIN
G55: T Shirts | K55: =(I55-H55)*J55 -> 0
B56: Personnel (show side) | G56: Vinyle | K56: =(I56-H56)*J56 -> 0
B57: Sound Engeener | E57: =C54*D54 -> 0 | G57: Poster | K57: =(I57-H57)*J57 -> 0
B58: Light Engeener | E58: =C55*D55 -> 0 | G58: Goodies | K58: =(I58-H58)*J58 -> 0
B59: Roads / Crew | E59: =C56*D56 -> 0 | G59: TOTAL MERCH NET MARGIN | K59: =SUM(K55:K58) -> 0
E60: =C57*D57 -> 0
E61: =C58*D58 -> 0
B62: Production / stage manager | E62: =C59*D59 -> 0 | G62: NET RESULT = (Ticket + Other revenues + Merch) – Expenses – Commissions | H62: =K65-E69 -> 0
E63: =C60*D60 -> 0
B64: Miscellaneous | E64: =C61*D61 -> 0
B65: Subtotal Personnel (show side) | E65: =SUM(E54:E61) -> 0 | G65: TOTAL REVENUE | K65: =K59+H43+H31 -> 0
B69: TOTAL EXPENSES | E69: =E66+E54+E46+E36+E22 -> 0

Sheet Regional Tour
B1: SHOW COST (PLATEAU) · Regional Dates — Performance fee / Guarantee model
B2: ★ EMPLOYER SOCIAL CHARGES RATE
B3: ★ FOREIGN ARTIST WITHHOLDING TAX
B4: ★ MANAGEMENT COMMISSION RATE
B5: ★ BOOKING AGENT COMMISSION RATE
B7: Artist: | C7: =Summary!C4 -> 0
B8: Tour name:
B9: Start date:
B10: End date:
B11: Duration: | C11: =IF(AND(C9<>"",C10<>""),C10-C9,"") | D11: =IF(AND(C9<>"",C10<>""),ROUND((C10-C9)/30,1),"")
B12: Nb of Shows:
B14: POSITION | C14: FEE / SHOW | D14: GROSS × 16 SHOWS
B17: BLOC 1 · SHOW COST
B19: Lead Artist
B20: Lead Artist | D20: =C20*$C$12 -> 0
B21: Subtotal gross fees | D21: =SUM(D20:D20) -> 0
B22: Employer social charges (★) | D22: =E2*D21 -> 0
B23: Foreign artist withholding (★) | D23: =E3*D21 -> 0
B24: TOTAL LEAD ARTIST PAYROLL | D24: =D21+D22+D23 -> 0
B26: Band Members
B27: Singer | D27: =C27*$C$12 -> 0
B28: Keys | D28: =C28*$C$12 -> 0
B29: Drums | D29: =C29*$C$12 -> 0
B30: Bass | D30: =C30*$C$12 -> 0
D31: =C31*$C$12 -> 0
D32: =C32*$C$12 -> 0
B33: Subtotal gross fees | D33: =SUM(D27:D32) -> 0
B34: Employer social charges (★) — local musicians | D34: =E2*(D27+D28+D29+D30) -> 0
B35: Withholding tax (★) — foreign artists | D35: =E3*(D31+D32) -> 0
B36: TOTAL BAND MEMBERS PAYROLL | D36: =D33+D34+D35 -> 0
B38: Technical Crew
B39: General Stage Manager | D39: =C39*$C$12 -> 0
B40: Sound Engineer (FOH) | D40: =C40*$C$12 -> 0
B41: Lighting Designer | D41: =C41*$C$12 -> 0
B42: Backline Tech | D42: =C42*$C$12 -> 0
B43: Tour Manager | D43: =C43*$C$12 -> 0
B44: Roads / Crew | D44: =C44*$C$12 -> 0
B45: Subtotal gross fees | D45: =SUM(D39:D44) -> 0
B46: Employer social charges (★) | D46: =E2*D45 -> 0
B47: Foreign artist withholding (★) | D47: =E3*D45 -> 0
B48: TOTAL TECHNICAL CREW PAYROLL | D48: =D45+D46+D47 -> 0
B50: Technical / Equipment
B51: Sound system (if not provided by venue)
B52: Lighting rig (if needed)
B53: Backline rental
B54: ATA Carnet / Customs
B55: Consumables
B56: Miscellaneous
B57: TOTAL TECHNICAL / EQUIPMENT | D57: =SUM(D51:D56) -> 0
B59: Transport
B60: Tour bus / Minibus rental
B61: Van / VL rental
B62: Fuel & Tolls
B63: Flights | C63: =6*500 -> 3000
B64: Train
B65: Taxis / Parking / Miscellaneous
B66: TOTAL TRANSPORT | D66: =SUM(D60:D65) -> 0
B68: Accommodation & Meals
B69: Hotel – Artists | C69: 0
B70: Hotel – Tech crew | C70: 0
B71: Hotel – Off days
B72: Meals / Catering | C72: 0
B73: Travel day allowances
B74: Miscellaneous
B75: TOTAL ACCOMMODATION & MEALS | D75: =SUM(D69:D74) -> 0
B77: Administrative & Commissions
B78: Admin / logistics (10% payroll estimate) | D78: =0.1*(D24+D36+D48) -> 0
B79: Management commission (★) | D79: =E4*(D24+D36) -> 0
B80: Booking agent commission (★) | D80: =E5*D24 -> 0
B81: Share of pre-production creation costs
B85: TOTAL SHOW COST (incl. all payroll + charges) | D85: =D24+D36+D48+D57+D66+D75+D78+D79+D80+D81 -> 0
B89: BLOC 2 · REVENUES
B91: SOURCE OF INCOME | C91: TOTAL
B92: Performance fees (all dates) → see Show Dates table below | C92: =F138 -> 0
B93: Co-production fee
B94: Subtotal Performance Fees | C94: =C92+C93 -> 0
B96: Grants & Subsidies (total amount, not per show)
B97: CMO / SACEM-equivalent performance royalties
B98: Public subsidy (AFAC, IFJ, Goethe, etc.)
B99: Other subsidy
B100: Subtotal Grants & Subsidies | C100: =SUM(C97:C99) -> 0
B102: TOTAL REVENUES (excl. merch) | C102: =C94+C100 -> 0
B105: MERCHANDISE
B106: PRODUCT | C106: UNIT COST | D106: SELLING PRICE | E106: QTY SOLD | F106: NET MARGIN
B107: Product 1 | F107: =(D107-C107)*E107 -> 0
B108: Product 2 | F108: =(D108-C108)*E108 -> 0
B109: Product 3 | F109: =(D109-C109)*E109 -> 0
B110: Product 4 | F110: =(D110-C110)*E110 -> 0
B111: TOTAL MERCH NET MARGIN | F111: =SUM(F107:F110) -> 0
B116: NET RESULT = Total Revenues + Merch – Total Show Cost | E116: =C102+F111-D85 -> 0
B119: SHOW DATES · PERFORMANCE FEES BY DATE
B120: → Fill one row per show · Performance Fee total auto-feeds revenues above
B121: # | C121: DATE | D121: CITY | E121: VENUE | F121: PERFORMANCE FEE | G121: NOTES
G122: lidaejeljidjaeljd
B138: TOTAL | F138: =SUM(F122:F137) -> 0
B139: AVERAGE PERFORMANCE FEE (for reference) | F139: =IFERROR(AVERAGEIF(F122:F137,"<>0"),0) -> 0

Sheet International Tour
B1: SHOW COST (PLATEAU) · International Dates — Performance fee / Guarantee model
B2: ★ EMPLOYER SOCIAL CHARGES RATE
B3: ★ FOREIGN ARTIST WITHHOLDING TAX
B4: ★ MANAGEMENT COMMISSION RATE
B5: ★ BOOKING AGENT COMMISSION RATE
B7: Artist: | C7: =Summary!C4 -> 0
B8: Tour name:
B9: Start date:
B10: End date:
B11: Duration: | C11: =IF(AND(C9<>"",C10<>""),C10-C9,"") | D11: =IF(AND(C9<>"",C10<>""),ROUND((C10-C9)/30,1),"")
B12: Nb of Shows:
B14: POSITION | C14: FEE / SHOW | D14: GROSS × 10 SHOWS
B17: BLOC 1 · SHOW COST
B19: Lead Artist
B20: Lead Artist | D20: =C20*$C$12 -> 0
B21: Subtotal gross fees | D21: =SUM(D20:D20) -> 0
B22: Employer social charges (★) | D22: =E2*D21 -> 0
B23: Foreign artist withholding (★) | D23: =E3*D21 -> 0
B24: TOTAL LEAD ARTIST PAYROLL | D24: =D21+D22+D23 -> 0
B26: Band Members
B27: Drummer | D27: =C27*$C$12 -> 0
B28: Bass Player | D28: =C28*$C$12 -> 0
B29: Keys | D29: =C29*$C$12 -> 0
B30: Oud / Guitar | D30: =C30*$C$12 -> 0
B31: Musician (foreign artist) | D31: =C31*$C$12 -> 0
B32: Musician (foreign artist) | D32: =C32*$C$12 -> 0
B33: Subtotal gross fees | D33: =SUM(D27:D32) -> 0
B34: Employer social charges (★) — local musicians | D34: =E2*(D27+D28+D29+D30) -> 0
B35: Withholding tax (★) — foreign artists | D35: =E3*(D31+D32) -> 0
B36: TOTAL BAND MEMBERS PAYROLL | D36: =D33+D34+D35 -> 0
B38: Technical Crew
B39: General Stage Manager | D39: =C39*$C$12 -> 0
B40: Sound Engineer (FOH) | D40: =C40*$C$12 -> 0
B41: Lighting Designer | D41: =C41*$C$12 -> 0
B42: Backline Tech | D42: =C42*$C$12 -> 0
B43: Tour Manager | D43: =C43*$C$12 -> 0
B44: Roads / Crew | D44: =C44*$C$12 -> 0
B45: Subtotal gross fees | D45: =SUM(D39:D44) -> 0
B46: Employer social charges (★) | D46: =E2*D45 -> 0
B47: Foreign artist withholding (★) | D47: =E3*D45 -> 0
B48: TOTAL TECHNICAL CREW PAYROLL | D48: =D45+D46+D47 -> 0
B50: Technical / Equipment
B51: Sound system (if not provided by venue)
B52: Lighting rig (if needed)
B53: Backline rental
B54: ATA Carnet / Customs
B55: Consumables
B56: Miscellaneous
B57: TOTAL TECHNICAL / EQUIPMENT | D57: =SUM(D51:D56) -> 0
B59: Transport
B60: Tour bus / Minibus rental
B61: Van / VL rental
B62: Fuel & Tolls
B63: Flights
B64: Train
B65: Taxis / Parking / Miscellaneous
B66: TOTAL TRANSPORT | D66: =SUM(D60:D65) -> 0
B68: Accommodation & Meals
B69: Hotel – Artists
B70: Hotel – Tech crew
B71: Hotel – Off days
B72: Meals / Catering
B73: Travel day allowances
B74: Miscellaneous
B75: TOTAL ACCOMMODATION & MEALS | D75: =SUM(D69:D74) -> 0
B77: Administrative & Commissions
B78: Admin / logistics (10% payroll estimate) | D78: =0.1*(D24+D36+D48) -> 0
B79: Management commission (★) | D79: =E4*(D24+D36) -> 0
B80: Booking agent commission (★) | D80: =E5*D24 -> 0
B81: Share of pre-production creation costs
B85: TOTAL SHOW COST (incl. all payroll + charges) | D85: =D24+D36+D48+D57+D66+D75+D78+D79+D80+D81 -> 0
B89: BLOC 2 · REVENUES
B91: SOURCE OF INCOME | C91: PER SHOW | D91: NB SHOWS | E91: TOTAL
B92: Performance fee (guarantee) | E92: =C92*D92 -> 0
B93: Co-production fee | E93: =C93*D93 -> 0
B94: Subtotal Performance Fees | E94: =SUM(E92:E93) -> 0
B96: Grants & Subsidies (total amount, not per show)
B97: Tour Support
B98: Public subsidy (AFAC, IFJ, Goethe, etc.)
B99: Other subsidy
B100: Subtotal Grants & Subsidies | E100: =SUM(E97:E99) -> 0
B102: TOTAL REVENUES (excl. merch) | E102: =E94+E100 -> 0
B105: MERCHANDISE
B106: PRODUCT | C106: UNIT COST | D106: SELLING PRICE | E106: QTY SOLD | F106: NET MARGIN
B107: Product 1 | F107: =(D107-C107)*E107 -> 0
B108: Product 2 | F108: =(D108-C108)*E108 -> 0
B109: Product 3 | F109: =(D109-C109)*E109 -> 0
B110: Product 4 | F110: =(D110-C110)*E110 -> 0
B111: TOTAL MERCH NET MARGIN | F111: =SUM(F107:F110) -> 0
B116: BLOC 3 · NET RESULT = Revenues – Show Cost | E116: =(E102+E112)-D85 -> 0

Sheet Major Show
B1: MAJOR SHOW · SELF-PRODUCED DATE · LARGE VENUE
B2: ★ EMPLOYER SOCIAL CHARGES RATE
B3: ★ FOREIGN ARTIST WITHHOLDING TAX
B4: ★ MANAGEMENT COMMISSION RATE
B5: ★ BOOKING AGENT COMMISSION RATE
B7: Artist: | C7: =Summary!C4 -> 0
B8: Date:
B9: Venue:
B10: City:
B11: Capacity (Jauge):
B13: EXPENSES | C13: UNIT COST | D13: QTY | E13: TOTAL HT | G13: TICKETING STRUCTURE
B14: Venue | G14: Capacity (Jauge)
B15: Venue rental (fixed fee) | E15: =C15*D15 -> 0 | G15: Invitations (comps)
B16: Venue rental (variable %) | E16: =C16*D16 -> 0 | G16: Venue servitudes
B17: Video recording / Broadcast | E17: =C17*D17 -> 0 | G17: Tickets to sell | H17: =H14-H15-H16 -> 0
B18: Overtime hours | E18: =C18*D18 -> 0
B19: Ticketing / box-office fees | E19: =C19*D19 -> 0 | G19: TICKET PRICES
B20: Security provision | E20: =C20*D20 -> 0 | G20: Presale price
B21: Subtotal Venue | E21: =SUM(E15:E20) -> 0 | G21: Door price — auto: presale × 1.25 | H21: =H20*1.25 -> 0
B23: Artist Bill (incl. payroll charges) | G23: TICKET SALES
B24: Lead Artist | E24: =C24*D24 -> 0 | G24: Presale tickets sold
B25: Drummer | E25: =C25*D25 -> 0 | G25: Presale revenue | H25: =H20*H24 -> 0
B26: Bass Player | E26: =C26*D26 -> 0 | G26: Door tickets sold
B27: Keys | E27: =C27*D27 -> 0 | G27: Door revenue | H27: =H21*H26 -> 0
B28: Musician (foreign artist) | E28: =C28*D28 -> 0 | G28: GROSS TICKET REVENUE (TTC) | H28: =H25+H27 -> 0
B29: Musician (foreign artist) | E29: =C29*D29 -> 0
B30: Subtotal gross fees (Artist Bill) | E30: =SUM(E24:E29) -> 0 | G30: TAXES & DEDUCTIONS (Jordan)
B31: Employer social charges (★) — local musicians | E31: =E2*(E24+E25+E26+E27) -> 0 | G31: GST / Sales Tax on tickets (~16% Jordan — to confirm) | H31: =0.16*H28 -> 0
B32: Withholding tax (★) — foreign artists | E32: =E3*(E28+E29) -> 0 | G32: Entertainment / ticketing tax (rate TBC)
B33: TOTAL ARTIST BILL PAYROLL | E33: =E30+E31+E32 -> 0 | G33: Other local levies
G34: TOTAL TAXES & DEDUCTIONS | H34: =SUM(H31:H33) -> 0
B35: Production Tech | G35: NET TICKET REVENUE | H35: =H28-H34 -> 0
B36: Sound system rental | E36: =C36*D36 -> 0
B37: Lighting rig rental | E37: =C37*D37 -> 0 | G37: OTHER REVENUES
B38: Video / LED wall | E38: =C38*D38 -> 0 | G38: Crowdfunding
B39: Backline rental | E39: =C39*D39 -> 0 | G39: Sponsorship / brand partnership
B40: Rigging / Stage | E40: =C40*D40 -> 0 | G40: TOTAL OTHER REVENUES | H40: =H38+H39 -> 0
B41: Special effects | E41: =C41*D41 -> 0
B42: Miscellaneous | E42: =C42*D42 -> 0 | G42: COMMISSIONS
B43: Subtotal Production Tech | E43: =SUM(E36:E42) -> 0 | G43: Management commission (★) | H43: =E4*(H35+H40) -> 0
G44: Booking agent commission (★) | H44: =E5*H35 -> 0
B45: Marketing & Promotion
B46: Social media ads (Meta / TikTok / YouTube) | E46: =C46*D46 -> 0 | G46: BREAK-EVEN
B47: Radio / TV spots | E47: =C47*D47 -> 0 | G47: Min tickets to sell (total expenses ÷ avg net price) | H47: =IFERROR(ROUND(E69/((H35)/(H24+H26+1)),0),"fill ticket data") -> fill ticket data
B48: Print (posters, flyers, banners) | E48: =C48*D48 -> 0 | G48: Break-even as % of capacity | H48: =IFERROR(ROUND(E69/((H35)/(H24+H26+1))/H14,3),"fill data") -> fill data
B49: Press / PR agency fees | E49: =C49*D49 -> 0
B50: Street marketing / crew | E50: =C50*D50 -> 0 | G50: MERCHANDISE
B51: Influencer / content creator fees | E51: =C51*D51 -> 0 | G51: PRODUCT / ITEM | H51: NET MARGIN
B52: Ticketing platform commission | E52: =C52*D52 -> 0 | G52: → See Merch detail tab for cost/price/qty breakdown
B53: Miscellaneous promo | E53: =C53*D53 -> 0 | G53: Product 1
B54: Subtotal Marketing & Promotion | E54: =SUM(E46:E53) -> 0 | G54: Product 2
G55: Product 3
B56: Personnel (show side) | G56: Product 4
B57: Security chief | E57: =C57*D57 -> 0 | G57: TOTAL MERCH NET MARGIN | H57: =SUM(H53:H56) -> 0
B58: Security agents | E58: =C58*D58 -> 0
B59: Roads / Crew | E59: =C59*D59 -> 0 | G59: NET RESULT = (Ticket + Other revenues + Merch) – Expenses – Commissions | H59: =H35+H40+H57-H43-H44-E69 -> 0
B60: Catering staff | E60: =C60*D60 -> 0
B61: Box-office cashiers | E61: =C61*D61 -> 0
B62: Production manager | E62: =C62*D62 -> 0
B63: Stage manager | E63: =C63*D63 -> 0
B64: Miscellaneous | E64: =C64*D64 -> 0
B65: Subtotal Personnel (show side) | E65: =SUM(E57:E64) -> 0
B69: TOTAL EXPENSES | E69: =E21+E33+E43+E54+E65 -> 0
